hh_ui_check/__init__.py
hh_ui_check/__main__.py
hh_ui_check/diff.py
hh_ui_check/hist_compare.py
hh_ui_check/horizen.py
hh_ui_check/overlapping.py
hh_ui_check/substract.py
hh_ui_check-0.1.6.dist-info/METADATA
hh_ui_check-0.1.6.dist-info/WHEEL
hh_ui_check-0.1.6.dist-info/entry_points.txt
hh_ui_check-0.1.6.dist-info/RECORD
