Metadata-Version: 2.1
Name: hh-ui-check
Version: 0.1.6
Summary: 
Author: 林明超
Author-email: mingchao.lin@zeekrlife.com
Requires-Python: >=3.10,<4.0
Classifier: Programming Language :: Python :: 3
Classifier: Programming Language :: Python :: 3.10
Classifier: Programming Language :: Python :: 3.11
Requires-Dist: matplotlib (>=3.7.1,<4.0.0)
Requires-Dist: numpy (>=1.24.3,<2.0.0)
Requires-Dist: opencv-python (>=4.7.0.72,<5.0.0.0)
